LICENSE
biasedclassifier/__init__.py
biasedclassifier-0.3.1.dist-info/LICENSE
biasedclassifier-0.3.1.dist-info/WHEEL
biasedclassifier-0.3.1.dist-info/METADATA
biasedclassifier-0.3.1.dist-info/RECORD
