Metadata-Version: 2.1
Name: biasedclassifier
Version: 0.3.1
Summary: 
Home-page: https://rparraca.github.io/BiasedClassifier/
License: MIT
Keywords: imbalanced,classification,random forest
Author: Rodrigo Parra
Author-email: contact@rodrigo-parra.com
Requires-Python: >=3.7,<4.0
Classifier: License :: OSI Approved :: MIT License
Classifier: Programming Language :: Python :: 3
Classifier: Programming Language :: Python :: 3.7
Classifier: Programming Language :: Python :: 3.8
Requires-Dist: scikit-learn (>=0.23.2,<0.24.0)
Project-URL: Repository, https://github.com/rparraca/BiasedClassifier
